setup.cfg
setup.py
jitpy/__init__.py
jitpy/exc.py
jitpy/pypy_side.py
jitpy/wrapper.py
jitpy.egg-info/PKG-INFO
jitpy.egg-info/SOURCES.txt
jitpy.egg-info/dependency_links.txt
jitpy.egg-info/not-zip-safe
jitpy.egg-info/top_level.txt