Metadata-Version: 1.0
Name: jitpy
Version: 0.1.3
Summary: A library to embed PyPy in CPython.
Home-page: http://jitpy.readthedocs.org
Author: Maciej Fijalkowski
Author-email: jitpy@googlegroups.com
License: MIT
Platform: UNKNOWN
